setup.cfg
setup.py
phoneid/__init__.py
phoneid/axis.py
phoneid/byru.py
phoneid/generator.py
phoneid/indosat.py
phoneid/lippo.py
phoneid/sampoerna.py
phoneid/smartfren.py
phoneid/telkomsel.py
phoneid/three.py
phoneid/xl.py
phoneid.egg-info/PKG-INFO
phoneid.egg-info/SOURCES.txt
phoneid.egg-info/dependency_links.txt
phoneid.egg-info/requires.txt
phoneid.egg-info/top_level.txt