Metadata-Version: 1.1
Name: phoneid
Version: 0.1.3
Summary: A library to generate Indonesian phone numbers
Home-page: https://github.com/coralhq/phone-id
Author: Batista Harahap
Author-email: batista@bango29.com
License: UNKNOWN
Download-URL: https://github.com/coralhq/phone-id/archive/0.1.2.tar.gz
Keywords: phone,number,indonesia,telco
Platform: UNKNOWN
